{
  "Component-dbg.js": 1572950435903,
  "Component-preload.js": 1572950435983,
  "Component.js": 1572943182000,
  "controller/App-dbg.controller.js": 1572950435903,
  "controller/App.controller.js": 1572943182000,
  "controller/BolsasPublicadas-dbg.controller.js": 1572950435903,
  "controller/BolsasPublicadas.controller.js": 1572943182000,
  "controller/ControladorBase-dbg.js": 1572950435903,
  "controller/ControladorBase.js": 1572943182000,
  "controller/DatosSolicitud-dbg.controller.js": 1572950435903,
  "controller/DatosSolicitud.controller.js": 1572943182000,
  "controller/Detalle-dbg.controller.js": 1572950435903,
  "controller/Detalle.controller.js": 1572943182000,
  "controller/DetalleSolicitud-dbg.controller.js": 1572950435903,
  "controller/DetalleSolicitud.controller.js": 1572943182000,
  "controller/Formatear-dbg.js": 1572950435903,
  "controller/Formatear.js": 1572943182000,
  "controller/ListaPuestos-dbg.controller.js": 1572950435903,
  "controller/ListaPuestos.controller.js": 1572943182000,
  "controller/ListaSolicitudes-dbg.controller.js": 1572950435903,
  "controller/ListaSolicitudes.controller.js": 1572943182000,
  "css/style-dbg.css": 1572950435913,
  "css/style.css": 1572943182000,
  "di.code-validation.core_issues.json": 1572950435273,
  "extended_runnable_file.html": 1572943182000,
  "i18n/i18n.properties": 1572943182000,
  "index.html": 1572943182000,
  "index_web.html": 1572943182000,
  "manifest-bundle.zip": 1572950436103,
  "manifest.json": 1572950435353,
  "model/models-dbg.js": 1572950435903,
  "model/models.js": 1572943182000,
  "neo-app.json": 1572950436013,
  "view/App.view.xml": 1572943182000,
  "view/BolsasPublicadas.view.xml": 1572943182000,
  "view/CopyOfMain.view.xml": 1572943182000,
  "view/DatosSolicitud.view.xml": 1572943182000,
  "view/Detalle.view.xml": 1572943182000,
  "view/DetalleSolicitud.view.xml": 1572943182000,
  "view/ListaPuestos.view.xml": 1572943182000,
  "view/ListaSolicitudes.view.xml": 1572943182000,
  "view/fragment/CreateDetalle.fragment.xml": 1572943182000,
  "view/fragment/DialogoOrdenacion.fragment.xml": 1572943182000,
  "view/fragment/DialogoPassword.fragment.xml": 1572943182000,
  "view/fragment/DisplayDetalle.fragment.xml": 1572943182000
}